[{"fw_binary_url":"https://zigbee-ota.sonoff.tech/releases/snzb-05p_v1.0.2.ota","fw_file_version":4098,"fw_filesize":267632,"fw_image_type":2059,"fw_manufacturer_id":4742,"model_id":"SNZB-05P"},{"fw_binary_url":"https://zigbee-ota.sonoff.tech/releases/zbminir2_v1.0.2.ota","fw_file_version":4098,"fw_filesize":275788,"fw_image_type":8,"fw_manufacturer_id":4742,"model_id":"ZBMINIR2"},{"fw_binary_url":"https://zigbee-ota.sonoff.tech/releases/snzb-02dr2_v1.0.3.ota","fw_file_version":4099,"fw_filesize":212336,"fw_image_type":2064,"fw_manufacturer_id":4742,"model_id":"SNZB-02DR2"},{"fw_binary_url":"https://zigbee-ota.sonoff.tech/releases/zbm5-120-zed_v1.0.4.ota","fw_file_version":4100,"fw_filesize":273908,"fw_image_type":9,"fw_manufacturer_id":4742,"model_id":"ZBM5-2C-120"},{"fw_binary_url":"https://zigbee-ota.sonoff.tech/releases/zbm5-120-zr_v1.0.4.ota","fw_file_version":4100,"fw_filesize":294932,"fw_image_type":10,"fw_manufacturer_id":4742,"model_id":"ZBM5-2C-120"},{"fw_binary_url":"https://zigbee-ota.sonoff.tech/releases/zbm5-120-zr_v1.0.4.ota","fw_file_version":4100,"fw_filesize":294932,"fw_image_type":10,"fw_manufacturer_id":4742,"model_id":"ZBM5-1C-120"},{"fw_binary_url":"https://zigbee-ota.sonoff.tech/releases/zbm5-120-zr_v1.0.4.ota","fw_file_version":4100,"fw_filesize":294932,"fw_image_type":10,"fw_manufacturer_id":4742,"model_id":"ZBM5-3C-120"},{"fw_binary_url":"https://zigbee-ota.sonoff.tech/releases/zbm5-120-zr_v1.0.4.ota","fw_file_version":4100,"fw_filesize":294932,"fw_image_type":10,"fw_manufacturer_id":4742,"model_id":"ZBM5-1C-80"},{"fw_binary_url":"https://zigbee-ota.sonoff.tech/releases/zbm5-120-zr_v1.0.4.ota","fw_file_version":4100,"fw_filesize":294932,"fw_image_type":10,"fw_manufacturer_id":4742,"model_id":"ZBM5-2C-80"},{"fw_binary_url":"https://zigbee-ota.sonoff.tech/releases/zbm5-120-zr_v1.0.4.ota","fw_file_version":4100,"fw_filesize":294932,"fw_image_type":10,"fw_manufacturer_id":4742,"model_id":"ZBM5-3C-80"},{"fw_binary_url":"https://zigbee-ota.sonoff.tech/releases/zbm5-120-zr_v1.0.4.ota","fw_file_version":4100,"fw_filesize":294932,"fw_image_type":10,"fw_manufacturer_id":4742,"model_id":"ZBM5-1C-86"},{"fw_binary_url":"https://zigbee-ota.sonoff.tech/releases/zbm5-120-zr_v1.0.4.ota","fw_file_version":4100,"fw_filesize":294932,"fw_image_type":10,"fw_manufacturer_id":4742,"model_id":"ZBM5-2C-86"},{"fw_binary_url":"https://zigbee-ota.sonoff.tech/releases/zbm5-120-zr_v1.0.4.ota","fw_file_version":4100,"fw_filesize":294932,"fw_image_type":10,"fw_manufacturer_id":4742,"model_id":"ZBM5-3C-86"},{"fw_binary_url":"https://zigbee-ota.sonoff.tech/releases/zbm5-120-zed_v1.0.4.ota","fw_file_version":4100,"fw_filesize":273908,"fw_image_type":9,"fw_manufacturer_id":4742,"model_id":"ZBM5-1C-120"},{"fw_binary_url":"https://zigbee-ota.sonoff.tech/releases/zbm5-120-zed_v1.0.4.ota","fw_file_version":4100,"fw_filesize":273908,"fw_image_type":9,"fw_manufacturer_id":4742,"model_id":"ZBM5-3C-120"},{"fw_binary_url":"https://zigbee-ota.sonoff.tech/releases/zbm5-120-zed_v1.0.4.ota","fw_file_version":4100,"fw_filesize":273908,"fw_image_type":9,"fw_manufacturer_id":4742,"model_id":"ZBM5-1C-80"},{"fw_binary_url":"https://zigbee-ota.sonoff.tech/releases/zbm5-120-zed_v1.0.4.ota","fw_file_version":4100,"fw_filesize":273908,"fw_image_type":9,"fw_manufacturer_id":4742,"model_id":"ZBM5-2C-80"},{"fw_binary_url":"https://zigbee-ota.sonoff.tech/releases/zbm5-120-zed_v1.0.4.ota","fw_file_version":4100,"fw_filesize":273908,"fw_image_type":9,"fw_manufacturer_id":4742,"model_id":"ZBM5-3C-80"},{"fw_binary_url":"https://zigbee-ota.sonoff.tech/releases/zbm5-120-zed_v1.0.4.ota","fw_file_version":4100,"fw_filesize":273908,"fw_image_type":9,"fw_manufacturer_id":4742,"model_id":"ZBM5-1C-86"},{"fw_binary_url":"https://zigbee-ota.sonoff.tech/releases/zbm5-120-zed_v1.0.4.ota","fw_file_version":4100,"fw_filesize":273908,"fw_image_type":9,"fw_manufacturer_id":4742,"model_id":"ZBM5-2C-86"},{"fw_binary_url":"https://zigbee-ota.sonoff.tech/releases/zbm5-120-zed_v1.0.4.ota","fw_file_version":4100,"fw_filesize":273908,"fw_image_type":9,"fw_manufacturer_id":4742,"model_id":"ZBM5-3C-86"},{"fw_binary_url":"https://zigbee-ota.sonoff.tech/releases/snzb-06p_v1.0.5.ota","fw_file_version":4101,"fw_filesize":258206,"fw_image_type":2060,"fw_manufacturer_id":4742,"model_id":"SNZB-06P"},{"fw_binary_url":"https://zigbee-ota.sonoff.tech/releases/zbmicro_v1.0.5.ota","fw_file_version":4101,"fw_filesize":269220,"fw_image_type":7,"fw_manufacturer_id":4742,"model_id":"ZBMicro"},{"fw_binary_url":"https://zigbee-ota.sonoff.tech/releases/zbm5-120-zr_v1.0.6.ota","fw_file_version":4102,"fw_filesize":295468,"fw_image_type":10,"fw_manufacturer_id":4742,"model_id":"ZBM5-1C-120"},{"fw_binary_url":"https://zigbee-ota.sonoff.tech/releases/zbminir2_v1.0.8.ota","fw_file_version":4104,"fw_filesize":277180,"fw_image_type":8,"fw_manufacturer_id":4742,"model_id":"ZBMINIR2"},{"fw_binary_url":"https://zigbee-ota.sonoff.tech/releases/zigbeeminil2_100E_stand_ota_file.ota","fw_file_version":4110,"fw_filesize":259018,"fw_image_type":4,"fw_manufacturer_id":4742,"model_id":"ZBMINIL2"},{"fw_binary_url":"https://zigbee-ota.sonoff.tech/releases/snzb02lwd_v1.1.0.ota","fw_file_version":4352,"fw_filesize":167888,"fw_image_type":2061,"fw_manufacturer_id":4742,"model_id":"SNZB-02LWD"},{"fw_binary_url":"https://zigbee-ota.sonoff.tech/releases/snzb02ld_v1.1.0.ota","fw_file_version":4352,"fw_filesize":167888,"fw_image_type":2061,"fw_manufacturer_id":4742,"model_id":"SNZB-02LD"},{"fw_binary_url":"https://zigbee-ota.sonoff.tech/releases/snzb02wd_v1.1.0.ota","fw_file_version":4352,"fw_filesize":167888,"fw_image_type":2061,"fw_manufacturer_id":4742,"model_id":"SNZB-02WD"},{"fw_binary_url":"https://zigbee-ota.sonoff.tech/releases/86-0001-00001101.zigbee","fw_file_version":4353,"fw_filesize":131086,"fw_image_type":1,"fw_manufacturer_id":4742,"model_id":"ZBMINI-L"},{"fw_binary_url":"https://zigbee-ota.sonoff.tech/releases/trvzb_v1.3.0.ota","fw_file_version":4864,"fw_filesize":329856,"fw_image_type":8199,"fw_manufacturer_id":4742,"model_id":"TRVZB"},{"fw_binary_url":"https://zigbee-ota.sonoff.tech/releases/trvzb_v1.4.0.ota","fw_file_version":5120,"fw_filesize":332084,"fw_image_type":8199,"fw_manufacturer_id":4742,"model_id":"TRVZB"},{"fw_binary_url":"https://zigbee-ota.sonoff.tech/releases/trvzb_v1.4.1.ota","fw_file_version":5121,"fw_filesize":332092,"fw_image_type":8199,"fw_manufacturer_id":4742,"model_id":"TRVZB"},{"fw_binary_url":"https://zigbee-ota.sonoff.tech/releases/snzb-02p_v2.2.0.ota","fw_file_version":8704,"fw_filesize":260018,"fw_image_type":2055,"fw_manufacturer_id":4742,"model_id":"SNZB-02P"},{"fw_binary_url":"https://zigbee-ota.sonoff.tech/releases/snzb-02d_v2.3.0.ota","fw_file_version":8960,"fw_filesize":264118,"fw_image_type":2053,"fw_manufacturer_id":4742,"model_id":"SNZB-02D"}]